[
  {
    "name": "Preconfigured Exegol Resources Kit [PERK]",
    "description": "Add tools and customizations to Exegol images during deployment",
    "status": "active",
    "slug": "perk",
    "readme": "https://raw.githubusercontent.com/NorthernReach/PERK/refs/heads/main/README.md",
    "repo": "https://github.com/NorthernReach/PERK",
    "tags": []
  },
  {
    "name": "Contaigen",
    "description": "Docker container images tailored for security operations",
    "status": "active",
    "slug": "contaigen",
    "readme": "https://raw.githubusercontent.com/NorthernReach/contaigen/refs/heads/main/README.md",
    "repo": "https://github.com/NorthernReach/contaigen",
    "tags": []
  }
]
